[
  {
    "index": 1,
    "type": "image",
    "status": "success",
    "size": "104.1 KB"
  },
  {
    "index": 2,
    "type": "image",
    "status": "success",
    "size": "33.1 KB"
  },
  {
    "index": 3,
    "type": "image",
    "status": "success",
    "size": "159.0 KB"
  },
  {
    "index": 4,
    "type": "image",
    "status": "success",
    "size": "121.7 KB"
  },
  {
    "index": 5,
    "type": "image",
    "status": "success",
    "size": "96.8 KB"
  },
  {
    "index": 6,
    "type": "image",
    "status": "success",
    "size": "123.1 KB"
  },
  {
    "index": 7,
    "type": "image",
    "status": "success",
    "size": "144.7 KB"
  },
  {
    "index": 8,
    "type": "image",
    "status": "success",
    "size": "99.9 KB"
  },
  {
    "index": 9,
    "type": "image",
    "status": "success",
    "size": "106.0 KB"
  },
  {
    "index": 10,
    "type": "image",
    "status": "success",
    "size": "98.9 KB"
  }
]